[
  {
    "title": "Grande e non molto bella internamente",
    "rating": 3,
    "travelDate": "2024-02",
    "publishedDate": "2024-02-22",
    "text": "Esternamente si presenta bene e appare interessante. Gli interni non mi sono piaciuti molto così come non mi è piaciuta nemmeno la cattedrale di Cotonou. Sembra piastrellata come una piscina.",
    "url": "https://www.tripadvisor.com/ShowUserReviews-g293765-d8130241-r939362504-Cathedrale_Notre_Dame_de_l_Immaculee_Conception-Porto_Novo_Oueme_Department.html",
    "user": {
      "userId": "D6E3A66186552555A7CBD8C5B83B19A9",
      "name": "gKiarag",
      "contributions": {
        "totalContributions": 2046,
        "helpfulVotes": 1168
      },
      "username": "gKiarag",
      "userLocation": {
        "shortName": "Lugano",
        "name": "Lugano, Switzerland",
        "id": "188095"
      },
      "avatar": {
        "id": "215717913",
        "width": 3264,
        "height": 2448,
        "image": "https://dynamic-media-cdn.tripadvisor.com/media/photo-o/0c/db/98/19/82chiara82.jpg"
      },
      "link": "www.tripadvisor.com/Profile/gKiarag"
    },
    "ownerResponse": null,
    "placeInfo": {
      "id": "8130241",
      "name": "Cathedrale Notre Dame de l'Immaculee Conception",
      "rating": 4.1,
      "numberOfReviews": 8,
      "locationString": "Porto-Novo, Oueme Department",
      "latitude": 6.472118,
      "longitude": 2.619703,
      "webUrl": "https://www.tripadvisor.com/Attraction_Review-g293765-d8130241-Reviews-Cathedrale_Notre_Dame_de_l_Immaculee_Conception-Porto_Novo_Oueme_Department.html",
      "website": "http://www.gcatholic.org/churches/africa/3925.htm",
      "address": "RNIE1, Porto-Novo Benin",
      "addressObj": {
        "street1": "RNIE1",
        "street2": null,
        "city": "Porto-Novo",
        "state": null,
        "country": "Benin",
        "postalcode": null
      },
      "ratingHistogram": {
        "count1": 0,
        "count2": 0,
        "count3": 1,
        "count4": 5,
        "count5": 2
      }
    },
    "translated_title": "Grande e non molto bella internamente",
    "translated_text": "Esternamente si presenta bene e appears interesting. Gli interni non mi sono piaciuti molto così come non mi è piaciuta nemenno la cathedrale di Cotonou. Sembra piastrellata like a swimming pool.",
    "original_language": "fr"
  },
  {
    "title": "Cathédrale de l'Immaculée Conception , Style Classique Africain , très Lumineux !!",
    "rating": 4,
    "travelDate": "2021-10",
    "publishedDate": "2022-02-11",
    "text": "La cathédrale de Porto Novo , se situe dans le centre de la ville en venant de Cotonou par la RNIE1 , après avoir passé la place Toffa . Elle date de 1864 , mais est de conception moderne dans le style Africain , qui conserve les trois éléments classiques , nef avec collatéraux mais sans transept  , Chevet , et clocher déporté . En arrivant , on voit l'imposante façade à deux niveaux , qui comporte une grande entrée avec trois portes à voute en berceau . Au dessus , la façade prend la forme d'un chapiteau ouvert de lancettes en vitrail et d'un oculus . Les tons sont clairs avec un  fond rose pâle , aux bordures au ton ocre . La nef possède des collatéraux ouverts de grandes fenêtres à chapiteau en plein cintre très esthétiques . \nAu bout de la nef , le chevet , de forme arrondie , est éclairé par des lancettes en vitrail opaque blanc . Le clocher à trois niveaux , est de section carrée en maçonnerie avec , de sa base , des tourelles d'angle terminées par une coiffe  ocre . La partie basse du clocher , est surmontée par un élément identique mais plus petit , coiffé d'un édicule de section carrée , ouvert de petites alvéoles supportant une grande croix ocre , sur tous les côtés . \n\nEn passant le porche , on peut voir un intérieur très lumineux , avec une grande nef à voute en berceau , supportée par des grands piliers peints en bleu ciel . Les déambulatoires , qui bordent la nef , sont pourvus d'ouvertures qui illuminent l'édifice  et de petites chapelles . L'autel de forme simple , se situe sur une estrade au milieu de l'abside ouverte de vitraux blancs . Le fond de l'abside , est couvert de carreaux bleu ciel et supporte une statue de la Vierge Marie avec des tentures aux couleurs du Togo . Ce lieu semble pour moi , idéal pour le recueillement mais traduit aussi l'impression de la joie traditionnelle africaine .",
    "url": "https://www.tripadvisor.com/ShowUserReviews-g293765-d8130241-r827513163-Cathedrale_Notre_Dame_de_l_Immaculee_Conception-Porto_Novo_Oueme_Department.html",
    "user": {
      "userId": "5CF735F6DC0B7B5CE056BB05AC534F34",
      "name": "DanyEarth👍👌",
      "contributions": {
        "totalContributions": 33858,
        "helpfulVotes": 104580
      },
      "username": "danyEarth",
      "userLocation": {
        "shortName": "France",
        "name": "France",
        "id": "187070"
      },
      "avatar": {
        "id": "559006816",
        "width": 768,
        "height": 768,
        "image": "https://dynamic-media-cdn.tripadvisor.com/media/photo-o/21/51/c4/60/danytwo.jpg"
      },
      "link": "www.tripadvisor.com/Profile/danyEarth"
    },
    "ownerResponse": null,
    "placeInfo": {
      "id": "8130241",
      "name": "Cathedrale Notre Dame de l'Immaculee Conception",
      "rating": 4.1,
      "numberOfReviews": 8,
      "locationString": "Porto-Novo, Oueme Department",
      "latitude": 6.472118,
      "longitude": 2.619703,
      "webUrl": "https://www.tripadvisor.com/Attraction_Review-g293765-d8130241-Reviews-Cathedrale_Notre_Dame_de_l_Immaculee_Conception-Porto_Novo_Oueme_Department.html",
      "website": "http://www.gcatholic.org/churches/africa/3925.htm",
      "address": "RNIE1, Porto-Novo Benin",
      "addressObj": {
        "street1": "RNIE1",
        "street2": null,
        "city": "Porto-Novo",
        "state": null,
        "country": "Benin",
        "postalcode": null
      },
      "ratingHistogram": {
        "count1": 0,
        "count2": 0,
        "count3": 1,
        "count4": 5,
        "count5": 2
      }
    },
    "translated_title": "Cathedral of the Immaculate Conception, Classic African Style, very Bright!!",
    "translated_text": "Porto Novo Cathedral is located in the city center coming from Cotonou by the RNIE1, after passing Toffa Square. It dates from 1864, but is of modern design in the African style, which retains the three classical elements, nave with side aisles but without transept, apse, and offset bell tower. Upon arrival, we see the imposing two-level facade, which includes a large entrance with three barrel-vaulted doors. Above, the facade takes the form of a capital open with stained glass lancets and an oculus. The tones are light with a pale pink background, with ochre-toned borders. The nave has side aisles open with large windows with very aesthetic semicircular capitals. At the end of the nave, the apse, rounded in shape, is lit by lancets in opaque white stained glass. The three-level bell tower is square in masonry with, from its base, corner turrets finished with an ochre cap. The lower part of the bell tower is surmounted by an identical but smaller element, topped with a square-section aedicule, open with small alveoli supporting a large ochre cross on all sides. Passing through the porch, one can see a very bright interior, with a large nave with a barrel vault, supported by large pillars painted in sky blue. The ambulatories, which border the nave, are provided with openings which illuminate the building and small chapels. The altar of simple form, is located on a platform in the middle of the apse open with white stained glass windows. The back of the apse is covered with sky blue tiles and supports a statue of the Virgin Mary with hangings in the colors of Togo. This place seems to me to be ideal for meditation but also conveys the impression of traditional African joy.",
    "original_language": "fr"
  },
  {
    "title": "great church",
    "rating": 4,
    "travelDate": "2019-03",
    "publishedDate": "2019-03-22",
    "text": "the catholique church is well maintained , we where there just before mass and the church was full an experiance  with songs and dance. from there you have a good view over the new parlement building and good place to start walk to the market 1 km from there",
    "url": "https://www.tripadvisor.com/ShowUserReviews-g293765-d8130241-r660277745-Cathedrale_Notre_Dame_de_l_Immaculee_Conception-Porto_Novo_Oueme_Department.html",
    "user": {
      "userId": "B9B7A852B608EE4B9534321DE4AA93BD",
      "name": "didierg402",
      "contributions": {
        "totalContributions": 65,
        "helpfulVotes": 11
      },
      "username": "didierg402",
      "userLocation": {
        "shortName": "Roeselare",
        "name": "Roeselare, Belgium",
        "id": "641832"
      },
      "avatar": {
        "id": "51470210",
        "width": 300,
        "height": 450,
        "image": "https://dynamic-media-cdn.tripadvisor.com/media/photo-s/03/11/5f/82/didier-g.jpg"
      },
      "link": "www.tripadvisor.com/Profile/didierg402"
    },
    "ownerResponse": null,
    "placeInfo": {
      "id": "8130241",
      "name": "Cathedrale Notre Dame de l'Immaculee Conception",
      "rating": 4.1,
      "numberOfReviews": 8,
      "locationString": "Porto-Novo, Oueme Department",
      "latitude": 6.472118,
      "longitude": 2.619703,
      "webUrl": "https://www.tripadvisor.com/Attraction_Review-g293765-d8130241-Reviews-Cathedrale_Notre_Dame_de_l_Immaculee_Conception-Porto_Novo_Oueme_Department.html",
      "website": "http://www.gcatholic.org/churches/africa/3925.htm",
      "address": "RNIE1, Porto-Novo Benin",
      "addressObj": {
        "street1": "RNIE1",
        "street2": null,
        "city": "Porto-Novo",
        "state": null,
        "country": "Benin",
        "postalcode": null
      },
      "ratingHistogram": {
        "count1": 0,
        "count2": 0,
        "count3": 1,
        "count4": 5,
        "count5": 2
      }
    },
    "translated_title": "great church",
    "translated_text": "the catholique church is well maintained , we where there just before mass and the church was full an experiance  with songs and dance. from there you have a good view over the new parlement building and good place to start walk to the market 1 km from there",
    "original_language": "en"
  },
  {
    "title": "Bénin porto_novo",
    "rating": 5,
    "travelDate": "2018-05",
    "publishedDate": "2018-05-27",
    "text": "Située au coeur de la ville de porto-novo au bénin,la cathédrale notre dame de l'imaculé est l'une des plus anciens et populaires monuments de la ville de porto-novo au bénin",
    "url": "https://www.tripadvisor.com/ShowUserReviews-g293765-d8130241-r582973109-Cathedrale_Notre_Dame_de_l_Immaculee_Conception-Porto_Novo_Oueme_Department.html",
    "user": {
      "userId": "3316844732F91F05968116B533A4566F",
      "name": "Tessilimi Kamarou",
      "contributions": {
        "totalContributions": 1737,
        "helpfulVotes": 58
      },
      "username": "tessilimikamarou",
      "userLocation": {
        "shortName": "Porto-Novo",
        "name": "Porto-Novo, Benin",
        "id": "293765"
      },
      "avatar": {
        "id": "264996550",
        "width": 720,
        "height": 720,
        "image": "https://dynamic-media-cdn.tripadvisor.com/media/photo-o/0f/cb/86/c6/tessilimi-k.jpg"
      },
      "link": "www.tripadvisor.com/Profile/tessilimikamarou"
    },
    "ownerResponse": null,
    "placeInfo": {
      "id": "8130241",
      "name": "Cathedrale Notre Dame de l'Immaculee Conception",
      "rating": 4.1,
      "numberOfReviews": 8,
      "locationString": "Porto-Novo, Oueme Department",
      "latitude": 6.472118,
      "longitude": 2.619703,
      "webUrl": "https://www.tripadvisor.com/Attraction_Review-g293765-d8130241-Reviews-Cathedrale_Notre_Dame_de_l_Immaculee_Conception-Porto_Novo_Oueme_Department.html",
      "website": "http://www.gcatholic.org/churches/africa/3925.htm",
      "address": "RNIE1, Porto-Novo Benin",
      "addressObj": {
        "street1": "RNIE1",
        "street2": null,
        "city": "Porto-Novo",
        "state": null,
        "country": "Benin",
        "postalcode": null
      },
      "ratingHistogram": {
        "count1": 0,
        "count2": 0,
        "count3": 1,
        "count4": 5,
        "count5": 2
      }
    },
    "translated_title": "Benin porto_novo",
    "translated_text": "Located in the heart of the city of Porto-Novo in Benin, the Cathedral of Our Lady of the Immaculate is one of the oldest and most popular monuments in the city of Porto-Novo in Benin.",
    "original_language": "fr"
  },
  {
    "title": "Beautiful repainted church",
    "rating": 4,
    "travelDate": "2018-04",
    "publishedDate": "2018-05-08",
    "text": "We were only able to walk outside of the church but it was beautiful. It has been repainted recently and is right across the street from a park. It's worth a quick visit if you're in the area.",
    "url": "https://www.tripadvisor.com/ShowUserReviews-g293765-d8130241-r578902364-Cathedrale_Notre_Dame_de_l_Immaculee_Conception-Porto_Novo_Oueme_Department.html",
    "user": {
      "userId": "E638376258A6F1EE40B47E6B55188843",
      "name": "tenthlisten",
      "contributions": {
        "totalContributions": 366,
        "helpfulVotes": 163
      },
      "username": "tenthlisten",
      "userLocation": {
        "shortName": "San Francisco",
        "name": "San Francisco, California",
        "id": "60713"
      },
      "avatar": null,
      "link": "www.tripadvisor.com/Profile/tenthlisten"
    },
    "ownerResponse": null,
    "placeInfo": {
      "id": "8130241",
      "name": "Cathedrale Notre Dame de l'Immaculee Conception",
      "rating": 4.1,
      "numberOfReviews": 8,
      "locationString": "Porto-Novo, Oueme Department",
      "latitude": 6.472118,
      "longitude": 2.619703,
      "webUrl": "https://www.tripadvisor.com/Attraction_Review-g293765-d8130241-Reviews-Cathedrale_Notre_Dame_de_l_Immaculee_Conception-Porto_Novo_Oueme_Department.html",
      "website": "http://www.gcatholic.org/churches/africa/3925.htm",
      "address": "RNIE1, Porto-Novo Benin",
      "addressObj": {
        "street1": "RNIE1",
        "street2": null,
        "city": "Porto-Novo",
        "state": null,
        "country": "Benin",
        "postalcode": null
      },
      "ratingHistogram": {
        "count1": 0,
        "count2": 0,
        "count3": 1,
        "count4": 5,
        "count5": 2
      }
    },
    "translated_title": "Beautiful repainted church",
    "translated_text": "We were only able to walk outside of the church but it was beautiful. It has been repainted recently and is right across the street from a park. It's worth a quick visit if you're in the area.",
    "original_language": "en"
  },
  {
    "title": "église catholique",
    "rating": 5,
    "travelDate": "2016-11",
    "publishedDate": "2017-07-06",
    "text": "la cathédrale notre dame de l'immaculé se situe en pleine ville de porto_novo au bénin tout juste en face de place bayole",
    "url": "https://www.tripadvisor.com/ShowUserReviews-g293765-d8130241-r499210292-Cathedrale_Notre_Dame_de_l_Immaculee_Conception-Porto_Novo_Oueme_Department.html",
    "user": {
      "userId": "3316844732F91F05968116B533A4566F",
      "name": "Tessilimi Kamarou",
      "contributions": {
        "totalContributions": 1737,
        "helpfulVotes": 58
      },
      "username": "tessilimikamarou",
      "userLocation": {
        "shortName": "Porto-Novo",
        "name": "Porto-Novo, Benin",
        "id": "293765"
      },
      "avatar": {
        "id": "264996550",
        "width": 720,
        "height": 720,
        "image": "https://dynamic-media-cdn.tripadvisor.com/media/photo-o/0f/cb/86/c6/tessilimi-k.jpg"
      },
      "link": "www.tripadvisor.com/Profile/tessilimikamarou"
    },
    "ownerResponse": null,
    "placeInfo": {
      "id": "8130241",
      "name": "Cathedrale Notre Dame de l'Immaculee Conception",
      "rating": 4.1,
      "numberOfReviews": 8,
      "locationString": "Porto-Novo, Oueme Department",
      "latitude": 6.472118,
      "longitude": 2.619703,
      "webUrl": "https://www.tripadvisor.com/Attraction_Review-g293765-d8130241-Reviews-Cathedrale_Notre_Dame_de_l_Immaculee_Conception-Porto_Novo_Oueme_Department.html",
      "website": "http://www.gcatholic.org/churches/africa/3925.htm",
      "address": "RNIE1, Porto-Novo Benin",
      "addressObj": {
        "street1": "RNIE1",
        "street2": null,
        "city": "Porto-Novo",
        "state": null,
        "country": "Benin",
        "postalcode": null
      },
      "ratingHistogram": {
        "count1": 0,
        "count2": 0,
        "count3": 1,
        "count4": 5,
        "count5": 2
      }
    },
    "translated_title": "Catholic Church",
    "translated_text": "The Cathedral of Our Lady of the Immaculate is located in the heart of Porto-Novo in Benin, just opposite Place Bayole.",
    "original_language": "fr"
  },
  {
    "title": "Cathedrale Cotonou",
    "rating": 4,
    "travelDate": "2017-02",
    "publishedDate": "2017-02-03",
    "text": "\"Travel With VuAfrik at Benin\"\n\nThe cathedral Notre Dame de Miséricode, commonly known as Cotonou Cathedral is a Roman catholic cathedral, located near the Ancien pont bridge in Cotonou. It's noted for its distinct burgundy and white tiled architecture. Its tower stands towards the rear end left side of the main building. On 14 September 1955, It was promoted as the Metropolitan archidiocese of Cotonou.",
    "url": "https://www.tripadvisor.com/ShowUserReviews-g293765-d8130241-r456866847-Cathedrale_Notre_Dame_de_l_Immaculee_Conception-Porto_Novo_Oueme_Department.html",
    "user": {
      "userId": "59BCC7A50CE0CB6CFF6CB2011EEAF6DF",
      "name": "VuAfrik",
      "contributions": {
        "totalContributions": 18,
        "helpfulVotes": 5
      },
      "username": "VuAfrik",
      "userLocation": {
        "shortName": "Togo",
        "name": "Togo",
        "id": "293838"
      },
      "avatar": {
        "id": "234730213",
        "width": 576,
        "height": 576,
        "image": "https://dynamic-media-cdn.tripadvisor.com/media/photo-o/0d/fd/b2/e5/vuafrik.jpg"
      },
      "link": "www.tripadvisor.com/Profile/VuAfrik"
    },
    "ownerResponse": null,
    "placeInfo": {
      "id": "8130241",
      "name": "Cathedrale Notre Dame de l'Immaculee Conception",
      "rating": 4.1,
      "numberOfReviews": 8,
      "locationString": "Porto-Novo, Oueme Department",
      "latitude": 6.472118,
      "longitude": 2.619703,
      "webUrl": "https://www.tripadvisor.com/Attraction_Review-g293765-d8130241-Reviews-Cathedrale_Notre_Dame_de_l_Immaculee_Conception-Porto_Novo_Oueme_Department.html",
      "website": "http://www.gcatholic.org/churches/africa/3925.htm",
      "address": "RNIE1, Porto-Novo Benin",
      "addressObj": {
        "street1": "RNIE1",
        "street2": null,
        "city": "Porto-Novo",
        "state": null,
        "country": "Benin",
        "postalcode": null
      },
      "ratingHistogram": {
        "count1": 0,
        "count2": 0,
        "count3": 1,
        "count4": 5,
        "count5": 2
      }
    },
    "translated_title": "Cathedrale Cotonou",
    "translated_text": "\"Travel With VuAfrik at Benin\"\n\nThe cathedral Notre Dame de Miséricode, commonly known as Cotonou Cathedral is a Roman catholic cathedral, located near the Ancien pont bridge in Cotonou. It's noted for its distinct burgundy and white tiled architecture. Its tower stands towards the rear end left side of the main building. On 14 September 1955, It was promoted as the Metropolitan archidiocese of Cotonou.",
    "original_language": "en"
  },
  {
    "title": "Bel édifice et messe très animée",
    "rating": 4,
    "travelDate": "2015-08",
    "publishedDate": "2015-08-13",
    "text": "Messe très animée avec orchestre et chorale dans ce belle édifice très fréquenté par les habitants du quartier.",
    "url": "https://www.tripadvisor.com/ShowUserReviews-g293765-d8130241-r298934480-Cathedrale_Notre_Dame_de_l_Immaculee_Conception-Porto_Novo_Oueme_Department.html",
    "user": {
      "userId": "F323C5DF9F4DF7ADF35DF615C91D10EF",
      "name": "AJU92",
      "contributions": {
        "totalContributions": 91,
        "helpfulVotes": 45
      },
      "username": "AJU92",
      "userLocation": {
        "shortName": "Courbevoie",
        "name": "Courbevoie, France",
        "id": "196563"
      },
      "avatar": {
        "id": "452386603",
        "width": 1200,
        "height": 1200,
        "image": "https://dynamic-media-cdn.tripadvisor.com/media/photo-o/1a/f6/df/2b/default-avatar-2020-39.jpg"
      },
      "link": "www.tripadvisor.com/Profile/AJU92"
    },
    "ownerResponse": null,
    "placeInfo": {
      "id": "8130241",
      "name": "Cathedrale Notre Dame de l'Immaculee Conception",
      "rating": 4.1,
      "numberOfReviews": 8,
      "locationString": "Porto-Novo, Oueme Department",
      "latitude": 6.472118,
      "longitude": 2.619703,
      "webUrl": "https://www.tripadvisor.com/Attraction_Review-g293765-d8130241-Reviews-Cathedrale_Notre_Dame_de_l_Immaculee_Conception-Porto_Novo_Oueme_Department.html",
      "website": "http://www.gcatholic.org/churches/africa/3925.htm",
      "address": "RNIE1, Porto-Novo Benin",
      "addressObj": {
        "street1": "RNIE1",
        "street2": null,
        "city": "Porto-Novo",
        "state": null,
        "country": "Benin",
        "postalcode": null
      },
      "ratingHistogram": {
        "count1": 0,
        "count2": 0,
        "count3": 1,
        "count4": 5,
        "count5": 2
      }
    },
    "translated_title": "Beautiful building and very lively mass",
    "translated_text": "Very lively mass with orchestra and choir in this beautiful building very popular with local residents.",
    "original_language": "fr"
  }
]